README.md
setup.py
ITA_test3.egg-info/PKG-INFO
ITA_test3.egg-info/SOURCES.txt
ITA_test3.egg-info/dependency_links.txt
ITA_test3.egg-info/top_level.txt
hate_tweet_map/__init__.py
hate_tweet_map/database.py
hate_tweet_map/util.py
hate_tweet_map/manage_tweets/__init__.py
hate_tweet_map/tweets_processor/EntityLinker.py
hate_tweet_map/tweets_processor/MyTagMe.py
hate_tweet_map/tweets_processor/TweetProcessor.py
hate_tweet_map/tweets_processor/__init__.py
hate_tweet_map/tweets_searcher/SearchTweets.py
hate_tweet_map/tweets_searcher/__init__.py
hate_tweet_map/users_searcher/SearchUsers.py
hate_tweet_map/users_searcher/__init__.py
tests/__init__.py
tests/test_process_tweet.py
tests/test_twitter_search.py
tests/test_user_search.py
tests/test_util.py